designPR/__init__.py
designPR/main.py
designPR/test_gui.py
designPR/test_primer_design.py
DesignPR-0.2.4.dist-info/LICENSE
DesignPR-0.2.4.dist-info/METADATA
DesignPR-0.2.4.dist-info/WHEEL
DesignPR-0.2.4.dist-info/entry_points.txt
DesignPR-0.2.4.dist-info/top_level.txt
DesignPR-0.2.4.dist-info/RECORD
