Metadata-Version: 2.1
Name: DesignPR
Version: 0.2.4
Summary: A GUI tool for designing PCR primers
Home-page: https://github.com/aidamo1824/DesignPR
Author: 
Author-email: 
License: MIT
License-File: LICENSE
Requires-Dist: biopython >=1.80
Requires-Dist: tk
